{
    "pageNo":1,
    "pageSize":20,
    "totalCount":0,
    "totalPage":0,
    "extraData":null,
    "msg":0,
    "status":0,
    "data":
    {
        "orderNo":10000,
        "orderTime":"2016-11-11",
        "payTime":"欠款单",
        "orderType":"我不知道账单有哪些，随便写一个",
        "orderDesc":"http://img3.imgtn.bdimg.com/it/u=2598835504,72070733&fm=11&gp=0.jpg",
        "orderPriceTrade":"10000",
        "subUserName":"尹新林",
        "orderPayStatus":4,
        "orderPayStatusDesc":"订单的主人太穷，穷死了",
        "aisleId":"1",
        "payTypeName":"欠款",
        "arrivalPrice":203894,
        "orderFee":1000,
        "feeRate":0.35,
        "otherAccount":"吴友鹏",
        "otherName":"以为不远透露姓名的群众"
    }
}
